odoo/addons/hr_employee_ssn/README.rst
odoo/addons/hr_employee_ssn/__init__.py
odoo/addons/hr_employee_ssn/__manifest__.py
odoo/addons/hr_employee_ssn/i18n/de.po
odoo/addons/hr_employee_ssn/i18n/es_AR.po
odoo/addons/hr_employee_ssn/i18n/fr.po
odoo/addons/hr_employee_ssn/i18n/hr_employee_ssn.pot
odoo/addons/hr_employee_ssn/i18n/it.po
odoo/addons/hr_employee_ssn/readme/CONTRIBUTORS.md
odoo/addons/hr_employee_ssn/readme/DESCRIPTION.md
odoo/addons/hr_employee_ssn/static/description/icon.png
odoo/addons/hr_employee_ssn/static/description/index.html
odoo/addons/hr_employee_ssn/views/hr_employee_views.xml
odoo_addon_hr_employee_ssn-18.0.1.0.0.2.dist-info/METADATA
odoo_addon_hr_employee_ssn-18.0.1.0.0.2.dist-info/WHEEL
odoo_addon_hr_employee_ssn-18.0.1.0.0.2.dist-info/top_level.txt
odoo_addon_hr_employee_ssn-18.0.1.0.0.2.dist-info/RECORD
